<?xml version="1.0" encoding="UTF-8"?>
<bsmi>
  <row>
    <廠商代號>1S2I002</廠商代號>
    <廠商名稱>衛生福利部玉里醫院</廠商名稱>
    <廠址>花蓮縣玉里鎮中華路448號</廠址>
    <電話>03-8886141#2115</電話>
    <傳真>03-8980461</傳真>
    <登錄日期>2009-11-26 00:00:00.0</登錄日期>
    <登錄範圍 />
    <證書有效期限>2018/09/30</證書有效期限>
    <版本>05</版本>
  </row>
  <row>
    <廠商代號>1XDI001</廠商代號>
    <廠商名稱>亞洲水泥股份有限公司花蓮製造廠</廠商名稱>
    <廠址>花蓮縣新城鄉新城村新興路125號</廠址>
    <電話>(03)8612101轉204</電話>
    <傳真>(03)8612108</傳真>
    <登錄日期>2009-12-11 00:00:00.0</登錄日期>
    <登錄範圍 />
    <證書有效期限>2018/09/30</證書有效期限>
    <版本>03</版本>
  </row>
  <row>
    <廠商代號>2FBF001</廠商代號>
    <廠商名稱>九股山食品股份有限公司</廠商名稱>
    <廠址>宜蘭縣頭城鎮復興路37巷29號</廠址>
    <電話>03-9779988</電話>
    <傳真>03-9778081</傳真>
    <登錄日期>2006-09-18 00:00:00.0</登錄日期>
    <登錄範圍 />
    <證書有效期限>2018/09/17</證書有效期限>
    <版本>06</版本>
  </row>
  <row>
    <廠商代號>2S4Y002</廠商代號>
    <廠商名稱>台灣電力股份有限公司協和發電廠</廠商名稱>
    <廠址>基隆市文化路80號</廠址>
    <電話>02-24248111-310</電話>
    <傳真>02-24260450</傳真>
    <登錄日期>1997-10-27 00:00:00.0</登錄日期>
    <登錄範圍 />
    <證書有效期限>2018/09/22</證書有效期限>
    <版本>08</版本>
  </row>
  <row>
    <廠商代號>2XHY001</廠商代號>
    <廠商名稱>杏輝藥品工業股份有限公司</廠商名稱>
    <廠址>宜蘭縣冬山鄉中山路84號</廠址>
    <電話>03-9581101轉1245</電話>
    <傳真>03-9583309</傳真>
    <登錄日期>1997-10-30 00:00:00.0</登錄日期>
    <登錄範圍 />
    <證書有效期限>2018/09/22</證書有效期限>
    <版本>10</版本>
  </row>
  <row>
    <廠商代號>3A0Y017</廠商代號>
    <廠商名稱>威技電器股份有限公司</廠商名稱>
    <廠址>新北市中和區新民街112號8樓之8、之9</廠址>
    <電話>02-22265381</電話>
    <傳真>02-22265539</傳真>
    <登錄日期>2000-03-23 00:00:00.0</登錄日期>
    <登錄範圍 />
    <證書有效期限>2018/07/05</證書有效期限>
    <版本>08</版本>
  </row>
  <row>
    <廠商代號>3S4H001</廠商代號>
    <廠商名稱>台灣電力股份有限公司林口發電廠</廠商名稱>
    <廠址>新北市林口區下福里139-1號</廠址>
    <電話>26063222#326</電話>
    <傳真>02-26062261</傳真>
    <登錄日期>2006-11-07 00:00:00.0</登錄日期>
    <登錄範圍 />
    <證書有效期限>2018/09/04</證書有效期限>
    <版本>06</版本>
  </row>
  <row>
    <廠商代號>3S4T001</廠商代號>
    <廠商名稱>台灣電力股份有限公司林口發電廠</廠商名稱>
    <廠址>新北市林口區下福里139-1號</廠址>
    <電話>02-26062221-327</電話>
    <傳真>02-26062221</傳真>
    <登錄日期>2008-06-16 00:00:00.0</登錄日期>
    <登錄範圍 />
    <證書有效期限>2018/09/04</證書有效期限>
    <版本>05</版本>
  </row>
  <row>
    <廠商代號>3S8I009</廠商代號>
    <廠商名稱>經濟部(工商憑證管理中心)</廠商名稱>
    <廠址>台北市福州街15號</廠址>
    <電話>(02)23212200#307</電話>
    <傳真>(02)23410602</傳真>
    <登錄日期>2009-12-11 00:00:00.0</登錄日期>
    <登錄範圍 />
    <證書有效期限>2018/09/30</證書有效期限>
    <版本>04</版本>
  </row>
  <row>
    <廠商代號>3SCY002</廠商代號>
    <廠商名稱>台灣電力股份有限公司(營建處)</廠商名稱>
    <廠址>台北市羅斯福路3段242號16樓及17樓</廠址>
    <電話>02-22666934</電話>
    <傳真>02-23651630</傳真>
    <登錄日期>2003-04-24 00:00:00.0</登錄日期>
    <登錄範圍 />
    <證書有效期限>2018/04/29</證書有效期限>
    <版本>05</版本>
  </row>
  <row>
    <廠商代號>3TAE002</廠商代號>
    <廠商名稱>南亞塑膠工業股份有限公司林口二廠</廠商名稱>
    <廠址>新北市泰山區南林路102號</廠址>
    <電話>02-29019141</電話>
    <傳真>02-29080795</傳真>
    <登錄日期>1997-09-09 00:00:00.0</登錄日期>
    <登錄範圍 />
    <證書有效期限>2018/09/04</證書有效期限>
    <版本>08</版本>
  </row>
  <row>
    <廠商代號>3X0H002</廠商代號>
    <廠商名稱>南亞塑膠工業股份有限公司林口二廠</廠商名稱>
    <廠址>新北市泰山區南林路102號</廠址>
    <電話>02-27122211#5643</電話>
    <傳真>02-27178533</傳真>
    <登錄日期>2006-09-06 00:00:00.0</登錄日期>
    <登錄範圍 />
    <證書有效期限>2018/09/04</證書有效期限>
    <版本>07</版本>
  </row>
  <row>
    <廠商代號>3XEY007</廠商代號>
    <廠商名稱>泰新工業股份有限公司</廠商名稱>
    <廠址>新北市樹林區俊英街212號</廠址>
    <電話>02-26813301</電話>
    <傳真>02-26813305</傳真>
    <登錄日期>1997-09-08 00:00:00.0</登錄日期>
    <登錄範圍 />
    <證書有效期限>2018/11/22</證書有效期限>
    <版本>08</版本>
  </row>
  <row>
    <廠商代號>4A3Y006</廠商代號>
    <廠商名稱>宏泰電工股份有限公司南崁廠</廠商名稱>
    <廠址>桃園市蘆竹區南工路2段500號</廠址>
    <電話>02-27011000</電話>
    <傳真>02-27081100</傳真>
    <登錄日期>1994-08-01 00:00:00.0</登錄日期>
    <登錄範圍 />
    <證書有效期限>2018/07/16</證書有效期限>
    <版本>11</版本>
  </row>
  <row>
    <廠商代號>4A6Y010</廠商代號>
    <廠商名稱>士林電機廠股份有限公司新豐廠</廠商名稱>
    <廠址>新竹縣新豐鄉中崙村234號</廠址>
    <電話>03-5995111</電話>
    <傳真>03-5995259</傳真>
    <登錄日期>1997-06-05 00:00:00.0</登錄日期>
    <登錄範圍 />
    <證書有效期限>2018/08/03</證書有效期限>
    <版本>08</版本>
  </row>
  <row>
    <廠商代號>4FBF001</廠商代號>
    <廠商名稱>統一企業股份有限公司楊梅廠</廠商名稱>
    <廠址>桃園市楊梅區民富路1段301號</廠址>
    <電話>03-4784143#3260</電話>
    <傳真>03-4784616</傳真>
    <登錄日期>2006-04-18 00:00:00.0</登錄日期>
    <登錄範圍 />
    <證書有效期限>2018/12/22</證書有效期限>
    <版本>08</版本>
  </row>
  <row>
    <廠商代號>4M4H001</廠商代號>
    <廠商名稱>東培工業股份有限公司桃園廠</廠商名稱>
    <廠址>桃園市八德區介壽路一段600號</廠址>
    <電話>03-3613151#293</電話>
    <傳真>03-3628039</傳真>
    <登錄日期>2009-05-12 00:00:00.0</登錄日期>
    <登錄範圍 />
    <證書有效期限>2018/05/11</證書有效期限>
    <版本>03</版本>
  </row>
  <row>
    <廠商代號>4S2I001</廠商代號>
    <廠商名稱>衛生福利部桃園醫院(資訊室)</廠商名稱>
    <廠址>桃園市桃園區中山路1492號</廠址>
    <電話>03-3699721#3054</電話>
    <傳真>03-3605745</傳真>
    <登錄日期>2006-09-29 00:00:00.0</登錄日期>
    <登錄範圍 />
    <證書有效期限>2018/09/08</證書有效期限>
    <版本>06</版本>
  </row>
  <row>
    <廠商代號>4S8I001</廠商代號>
    <廠商名稱>新竹市稅務局</廠商名稱>
    <廠址>新竹市30041中央路112號</廠址>
    <電話>03-5225161-605</電話>
    <傳真>03-5241341</傳真>
    <登錄日期>2009-12-24 00:00:00.0</登錄日期>
    <登錄範圍 />
    <證書有效期限>2018/12/23</證書有效期限>
    <版本>06</版本>
  </row>
  <row>
    <廠商代號>4XFY009</廠商代號>
    <廠商名稱>國寶製煉油漆油墨股份有限公司銅鑼工廠</廠商名稱>
    <廠址>苗栗縣銅鑼鄉銅鑼村25鄰民治路39號</廠址>
    <電話>03-3983625</電話>
    <傳真>03-3983629</傳真>
    <登錄日期>1997-11-06 00:00:00.0</登錄日期>
    <登錄範圍 />
    <證書有效期限>2018/09/22</證書有效期限>
    <版本>07</版本>
  </row>
  <row>
    <廠商代號>5F8F002</廠商代號>
    <廠商名稱>中聯油脂股份有限公司</廠商名稱>
    <廠址>台中市清水區海濱里北堤路1之8號</廠址>
    <電話>04-26571112#261</電話>
    <傳真>04-26574289</傳真>
    <登錄日期>2012-10-23 00:00:00.0</登錄日期>
    <登錄範圍 />
    <證書有效期限>2018/10/22</證書有效期限>
    <版本>02</版本>
  </row>
  <row>
    <廠商代號>5S9Y003</廠商代號>
    <廠商名稱>財團法人自行車暨健康科技工業研究發展中心</廠商名稱>
    <廠址>台中市台中工業區三十七路17號</廠址>
    <電話>04-23501100ex107</電話>
    <傳真>04-23506624</傳真>
    <登錄日期>1997-09-26 00:00:00.0</登錄日期>
    <登錄範圍 />
    <證書有效期限>2018/09/22</證書有效期限>
    <版本>10</版本>
  </row>
  <row>
    <廠商代號>5S9Y005</廠商代號>
    <廠商名稱>財團法人車輛研究測試中心</廠商名稱>
    <廠址>彰化縣鹿港鎮鹿工南七路6號</廠址>
    <電話>04-7811222-2306</電話>
    <傳真>04-7811050、168</傳真>
    <登錄日期>1994-08-25 00:00:00.0</登錄日期>
    <登錄範圍 />
    <證書有效期限>2018/09/22</證書有效期限>
    <版本>10</版本>
  </row>
  <row>
    <廠商代號>5TCE001</廠商代號>
    <廠商名稱>陸軍兵工整備發展中心</廠商名稱>
    <廠址>南投縣集集鎮田寮里龍泉巷15號</廠址>
    <電話>049-2781294</電話>
    <傳真>049-2781408</傳真>
    <登錄日期>2003-01-27 00:00:00.0</登錄日期>
    <登錄範圍 />
    <證書有效期限>2018/09/14</證書有效期限>
    <版本>06</版本>
  </row>
  <row>
    <廠商代號>5TCY001</廠商代號>
    <廠商名稱>陸軍兵工整備發展中心</廠商名稱>
    <廠址>南投縣集集鎮田寮里龍泉巷15號</廠址>
    <電話>049-2781812</電話>
    <傳真>049-2781443</傳真>
    <登錄日期>1997-10-24 00:00:00.0</登錄日期>
    <登錄範圍 />
    <證書有效期限>2018/09/22</證書有效期限>
    <版本>09</版本>
  </row>
  <row>
    <廠商代號>5XEH002</廠商代號>
    <廠商名稱>台灣中油股份有限公司天然氣事業部台中液化天然氣廠</廠商名稱>
    <廠址>台中市梧棲區草湳里南堤路2段88號</廠址>
    <電話>04-26380739轉631</電話>
    <傳真>04-26308456</傳真>
    <登錄日期>2009-04-09 00:00:00.0</登錄日期>
    <登錄範圍 />
    <證書有效期限>2018/04/08</證書有效期限>
    <版本>03</版本>
  </row>
  <row>
    <廠商代號>5XET001</廠商代號>
    <廠商名稱>台灣中油股份有限公司天然氣事業部台中液化天然氣廠</廠商名稱>
    <廠址>台中市梧棲區草湳里南堤路2段88號</廠址>
    <電話>04-26380739轉633</電話>
    <傳真>04-26308170</傳真>
    <登錄日期>2009-04-09 00:00:00.0</登錄日期>
    <登錄範圍 />
    <證書有效期限>2018/04/08</證書有效期限>
    <版本>03</版本>
  </row>
  <row>
    <廠商代號>5XEY001</廠商代號>
    <廠商名稱>台塑生醫科技股份有限公司(彰化廠)</廠商名稱>
    <廠址>彰化市中山路3段359號</廠址>
    <電話>04-7236101ex330</電話>
    <傳真>04-7259243</傳真>
    <登錄日期>1994-04-13 00:00:00.0</登錄日期>
    <登錄範圍 />
    <證書有效期限>2018/06/16</證書有效期限>
    <版本>11</版本>
  </row>
  <row>
    <廠商代號>6A0Y009</廠商代號>
    <廠商名稱>宏昕電機股份有限公司</廠商名稱>
    <廠址>台南市永康區南興路105號</廠址>
    <電話>02-2716111</電話>
    <傳真>02-2716535</傳真>
    <登錄日期>1997-03-04 00:00:00.0</登錄日期>
    <登錄範圍 />
    <證書有效期限>2018/05/04</證書有效期限>
    <版本>08</版本>
  </row>
  <row>
    <廠商代號>6A3Y002</廠商代號>
    <廠商名稱>正規電線電纜工業股份有限公司</廠商名稱>
    <廠址>台南市新市區國際路16號</廠址>
    <電話>06-5995221#6</電話>
    <傳真>06-5995229</傳真>
    <登錄日期>1994-08-12 00:00:00.0</登錄日期>
    <登錄範圍 />
    <證書有效期限>2018/09/22</證書有效期限>
    <版本>08</版本>
  </row>
  <row>
    <廠商代號>6A3Y009</廠商代號>
    <廠商名稱>華光電線電纜股份有限公司</廠商名稱>
    <廠址>台南市官田區南廍里南廍120號</廠址>
    <電話>06-5792629</電話>
    <傳真>06-5793380</傳真>
    <登錄日期>1997-02-05 00:00:00.0</登錄日期>
    <登錄範圍 />
    <證書有效期限>2018/05/14</證書有效期限>
    <版本>09</版本>
  </row>
  <row>
    <廠商代號>6F3F004</廠商代號>
    <廠商名稱>台灣糖業股份有限公司畜殖事業部</廠商名稱>
    <廠址>台南市柳營區人和里義士路5段690號B棟</廠址>
    <電話>06-6223233#548</電話>
    <傳真>06-62236419</傳真>
    <登錄日期>2012-12-22 00:00:00.0</登錄日期>
    <登錄範圍 />
    <證書有效期限>2018/12/21</證書有效期限>
    <版本>01</版本>
  </row>
  <row>
    <廠商代號>6M8Y022</廠商代號>
    <廠商名稱>振鍵產業股份有限公司水上廠</廠商名稱>
    <廠址>嘉義縣水上鄉大崙村162號</廠址>
    <電話>05-3716358</電話>
    <傳真>05-3716039</傳真>
    <登錄日期>1997-08-12 00:00:00.0</登錄日期>
    <登錄範圍 />
    <證書有效期限>2018/09/22</證書有效期限>
    <版本>10</版本>
  </row>
  <row>
    <廠商代號>6X0E003</廠商代號>
    <廠商名稱>南亞塑膠工業股份有限公司嘉義廠及新港廠</廠商名稱>
    <廠址>嘉義縣太保市南新里北港路2段201號</廠址>
    <電話>05-2373711</電話>
    <傳真>05-2376195</傳真>
    <登錄日期>1997-12-18 00:00:00.0</登錄日期>
    <登錄範圍 />
    <證書有效期限>2018/09/14</證書有效期限>
    <版本>08</版本>
  </row>
  <row>
    <廠商代號>6X0Y017</廠商代號>
    <廠商名稱>隆輝安全帽有限公司</廠商名稱>
    <廠址>台南市永康區崑山里大灣路1020巷33號</廠址>
    <電話>06-2728270</電話>
    <傳真>06-2721581</傳真>
    <登錄日期>1997-01-09 00:00:00.0</登錄日期>
    <登錄範圍 />
    <證書有效期限>2018/08/10</證書有效期限>
    <版本>10</版本>
  </row>
  <row>
    <廠商代號>6X9Y001</廠商代號>
    <廠商名稱>康那香企業股份有限公司佳里廠</廠商名稱>
    <廠址>臺南市佳里區民安里同安寮77之1號</廠址>
    <電話>06-7946173#3270</電話>
    <傳真>06-7222495</傳真>
    <登錄日期>1994-11-25 00:00:00.0</登錄日期>
    <登錄範圍 />
    <證書有效期限>2018/09/10</證書有效期限>
    <版本>11</版本>
  </row>
  <row>
    <廠商代號>7S4E007</廠商代號>
    <廠商名稱>台灣電力股份有限公司大林發電廠</廠商名稱>
    <廠址>高雄市小港區大林路3號</廠址>
    <電話>07-8711151</電話>
    <傳真>07-8713760</傳真>
    <登錄日期>2006-03-14 00:00:00.0</登錄日期>
    <登錄範圍 />
    <證書有效期限>2018/06/06</證書有效期限>
    <版本>04</版本>
  </row>
  <row>
    <廠商代號>7S4Y031</廠商代號>
    <廠商名稱>台灣電力股份有限公司高屏發電廠</廠商名稱>
    <廠址>高雄市美濃區獅山里竹門20號</廠址>
    <電話>07-6851079 #22</電話>
    <傳真>07-6852335</傳真>
    <登錄日期>2006-12-28 00:00:00.0</登錄日期>
    <登錄範圍 />
    <證書有效期限>2018/09/22</證書有效期限>
    <版本>04</版本>
  </row>
  <row>
    <廠商代號>7S7E001</廠商代號>
    <廠商名稱>台灣電力股份有限公司輸變電工程處南區施工處</廠商名稱>
    <廠址>高雄市楠梓區旗楠路67號</廠址>
    <電話>07-3572290</電話>
    <傳真>07-3572198</傳真>
    <登錄日期>2006-05-09 00:00:00.0</登錄日期>
    <登錄範圍 />
    <證書有效期限>2018/05/08</證書有效期限>
    <版本>03</版本>
  </row>
  <row>
    <廠商代號>7XBY001</廠商代號>
    <廠商名稱>三戶保溫材料廠股份有限公司高雄廠</廠商名稱>
    <廠址>高雄市大寮區過溪里華一街525號</廠址>
    <電話>07-3312529</電話>
    <傳真>07-3313198</傳真>
    <登錄日期>1997-01-03 00:00:00.0</登錄日期>
    <登錄範圍 />
    <證書有效期限>2018/07/26</證書有效期限>
    <版本>09</版本>
  </row>
  <row>
    <廠商代號>7XEI001</廠商代號>
    <廠商名稱>台灣中油股份有限公司煉製事業部</廠商名稱>
    <廠址>高雄市左楠路2號</廠址>
    <電話>07-5824141#2189</電話>
    <傳真>07-3635108</傳真>
    <登錄日期>2006-12-26 00:00:00.0</登錄日期>
    <登錄範圍 />
    <證書有效期限>2018/09/30</證書有效期限>
    <版本>07</版本>
  </row>
  <row>
    <廠商代號>7XEI002</廠商代號>
    <廠商名稱>台灣中油股份有限公司煉製事業部大林煉油廠</廠商名稱>
    <廠址>高雄市小港區沿海四路50號</廠址>
    <電話>07-8715151</電話>
    <傳真>07-8712142</傳真>
    <登錄日期>2007-01-25 00:00:00.0</登錄日期>
    <登錄範圍 />
    <證書有效期限>2018/12/29</證書有效期限>
    <版本>07</版本>
  </row>
  <row>
    <廠商代號>8A0Y039</廠商代號>
    <廠商名稱>松下電器產業株式會社AP科技事業公司家電經營集團廚房器具經營單位神戶據點</廠商名稱>
    <廠址>日本兵庫縣神戶市西區高塚台1丁目5番1號</廠址>
    <電話>+81-78-992 9476</電話>
    <傳真>+81-78-992 9494</傳真>
    <登錄日期>2007-01-29 00:00:00.0</登錄日期>
    <登錄範圍 />
    <證書有效期限>2018/04/09</證書有效期限>
    <版本>06</版本>
  </row>
  <row>
    <廠商代號>8E1Y023</廠商代號>
    <廠商名稱>PIONEER MANUFACTURING (THAILAND) CO., LTD.</廠商名稱>
    <廠址>ROJANA INDUSTRIAL PARK, 1/31 MOO 5 TAMBOL KANHAM, AMPHUR U-THAI, PRANAKORNSRI-AYUTTHAYA 13210, THAILAND</廠址>
    <電話>33-(0)35226160-611</電話>
    <傳真 />
    <登錄日期>2006-09-22 00:00:00.0</登錄日期>
    <登錄範圍 />
    <證書有效期限>2018/05/12</證書有效期限>
    <版本>04</版本>
  </row>
  <row>
    <廠商代號>8E2Y009</廠商代號>
    <廠商名稱>富士通天電子(無錫)有限公司</廠商名稱>
    <廠址>中國江蘇省無錫市高新技術產業開發區新華路19號</廠址>
    <電話>0510-88662233</電話>
    <傳真>0510-88662299</傳真>
    <登錄日期>2012-11-26 00:00:00.0</登錄日期>
    <登錄範圍 />
    <證書有效期限>2018/04/14</證書有效期限>
    <版本>01</版本>
  </row>
  <row>
    <廠商代號>8X0Y002</廠商代號>
    <廠商名稱>越南隆輝實業有限公司</廠商名稱>
    <廠址>越南平陽省宜安市新東協坊神浪2工業區DT743路N號路23號</廠址>
    <電話>06-2728270#181</電話>
    <傳真>06-2721581</傳真>
    <登錄日期>2003-09-29 00:00:00.0</登錄日期>
    <登錄範圍 />
    <證書有效期限>2018/09/14</證書有效期限>
    <版本>08</版本>
  </row>
</bsmi>

